anyblok_pyramid_beaker/__init__.py
anyblok_pyramid_beaker/config.py
anyblok_pyramid_beaker/pyramid_config.py
anyblok_pyramid_beaker/release.py
anyblok_pyramid_beaker/bloks/__init__.py
anyblok_pyramid_beaker/tests/__init__.py
anyblok_pyramid_beaker/tests/test_configuration.py
anyblok_pyramid_beaker/tests/test_registry.py
anyblok_pyramid_beaker-1.1.1.dist-info/DESCRIPTION.rst
anyblok_pyramid_beaker-1.1.1.dist-info/METADATA
anyblok_pyramid_beaker-1.1.1.dist-info/RECORD
anyblok_pyramid_beaker-1.1.1.dist-info/WHEEL
anyblok_pyramid_beaker-1.1.1.dist-info/entry_points.txt
anyblok_pyramid_beaker-1.1.1.dist-info/metadata.json
anyblok_pyramid_beaker-1.1.1.dist-info/top_level.txt
