Metadata-Version: 2.0
Name: anyblok-pyramid-beaker
Version: 1.1.1
Summary: Beaker session for AnyBlok / Pyramid
Home-page: http://docs.anyblok-pyramid-beaker.anyblok.org/1.1.1
Author: Jean-Sébastien Suzanne
Author-email: jssuzanne@anybox.fr
License: MPL2
Platform: UNKNOWN
Classifier: Development Status :: 4 - Beta
Classifier: Intended Audience :: Developers
Classifier: Programming Language :: Python :: 3.2
Classifier: Programming Language :: Python :: 3.3
Classifier: Programming Language :: Python :: 3.4
Classifier: Topic :: Software Development :: Libraries :: Python Modules
Classifier: Framework :: Pyramid
Classifier: License :: OSI Approved :: Mozilla Public License 2.0 (MPL 2.0)
Requires-Dist: anyblok-pyramid (>=0.7.0)
Requires-Dist: pyramid-beaker
